lamrand/__init__.py
lamrand/lamrand.py
tests/__init__.py
tests/test_lamrand.py
LamRand-0.1.4.dist-info/LICENSE
LamRand-0.1.4.dist-info/METADATA
LamRand-0.1.4.dist-info/WHEEL
LamRand-0.1.4.dist-info/top_level.txt
LamRand-0.1.4.dist-info/RECORD
