Metadata-Version: 2.1
Name: LamRand
Version: 0.1.4
Summary: A high-quality random number generator library
Home-page: https://github.com/calpimm/LamRand
Author: Kutay Irmak
Author-email: kutayirmak@icloud.com
Classifier: Programming Language :: Python :: 3
Classifier: License :: OSI Approved :: MIT License
Classifier: Operating System :: OS Independent
Requires-Python: >=3.6
License-File: LICENSE
Requires-Dist: plaintext
Requires-Dist: openpyxl
Requires-Dist: scipy
